<Namespace Name="System.Web.DynamicData.ModelProviders">
  <Metadata><Meta Name="ms.openlocfilehash" Value="617e2623116d2d77ee56573e0daa5a2d35ed231c" /><Meta Name="ms.sourcegitcommit" Value="88014e1c5440e3df4f66ef04393854d15b1fd534" /><Meta Name="ms.translationtype" Value="MT" /><Meta Name="ms.contentlocale" Value="zh-CN" /><Meta Name="ms.lasthandoff" Value="09/05/2019" /><Meta Name="ms.locfileid" Value="70501008" /></Metadata><Docs>
    <summary><see cref="N:System.Web.DynamicData.ModelProviders" /> 命名空间包含定义 ASP.NET 动态数据提供程序的核心功能的类。</summary>
    <remarks>To be added.</remarks>
  </Docs>
</Namespace>