<Namespace Name="System.Web.Handlers">
  <Metadata><Meta Name="ms.openlocfilehash" Value="cb41c361eace73fa48e1d93677d1bd3fd4bf79c0" /><Meta Name="ms.sourcegitcommit" Value="c982ad9e10a242d90f1e631b5981570f9e5d9f34" /><Meta Name="ms.translationtype" Value="MT" /><Meta Name="ms.contentlocale" Value="zh-CN" /><Meta Name="ms.lasthandoff" Value="09/10/2020" /><Meta Name="ms.locfileid" Value="70623709" /></Metadata><Docs>
    <summary><see cref="N:System.Web.Handlers" /> 命名空间包含的 HTTP 处理程序类用于处理对 Web 服务器发出的请求。</summary>
    <remarks>To be added.</remarks>
  </Docs>
</Namespace>