<Namespace Name="System.Web.Globalization">
  <Metadata><Meta Name="ms.openlocfilehash" Value="d6dcf4b4b4f391b0b8d8dd944571df96cb5927ae" /><Meta Name="ms.sourcegitcommit" Value="02dd069b9696eb4eee675b6541f86b2602076448" /><Meta Name="ms.translationtype" Value="MT" /><Meta Name="ms.contentlocale" Value="zh-CN" /><Meta Name="ms.lasthandoff" Value="10/20/2020" /><Meta Name="ms.locfileid" Value="92231863" /></Metadata><Docs>
    <summary>为本地化提供程序提供类和接口。</summary>
    <remarks>To be added.</remarks>
  </Docs>
</Namespace>
